actions/__init__.py
actions/axis_move.py
actions/base.py
actions/composite.py
actions/conditional.py
actions/config.py
actions/debug.py
actions/display.py
actions/easing.py
actions/formation.py
actions/helpers.py
actions/instant.py
actions/pattern.py
actions/physics_adapter.py
actions/pools.py
arcade_actions-0.10.7.dist-info/METADATA
arcade_actions-0.10.7.dist-info/WHEEL
arcade_actions-0.10.7.dist-info/licenses/LICENSE
arcade_actions-0.10.7.dist-info/RECORD
