Metadata-Version: 2.4
Name: arcade-actions
Version: 0.10.7
Summary: Extension library for Arcade 3.x, providing a high-level way to animate sprites with conditional actions.
Project-URL: Homepage, https://github.com/bcorfman/arcade_actions
Project-URL: Repository, https://github.com/bcorfman/arcade_actions
Project-URL: Documentation, https://deepwiki.com/bcorfman/arcade_actions
Project-URL: Issues, https://github.com/bcorfman/arcade_actions/issues
Author-email: Brandon Corfman <teacup_canny.5l@icloud.com>
License: MIT License
License-File: LICENSE
Keywords: actions,animation,arcade,gamedev,sprites
Classifier: Development Status :: 4 - Beta
Classifier: Intended Audience :: Developers
Classifier: License :: OSI Approved :: MIT License
Classifier: Programming Language :: Python :: 3
Classifier: Programming Language :: Python :: 3.10
Classifier: Programming Language :: Python :: 3.11
Classifier: Programming Language :: Python :: 3.12
Classifier: Programming Language :: Python :: 3.13
Classifier: Programming Language :: Python :: 3.14
Classifier: Topic :: Games/Entertainment
Classifier: Topic :: Software Development :: Libraries :: Python Modules
Requires-Python: >=3.10
Requires-Dist: arcade>=3.0.0.dev35
Requires-Dist: pyglet>=2.1.dev5
Requires-Dist: pysdl2>=0.9.16
Requires-Dist: screeninfo>=0.8.1
Provides-Extra: statemachine
Requires-Dist: python-statemachine>=2.5.0; extra == 'statemachine'
Provides-Extra: statemachine-diagrams
Requires-Dist: python-statemachine[diagrams]>=2.5.0; extra == 'statemachine-diagrams'
